liumify/__init__.py
liumify/components.py
liumify/core.py
liumify/templates/engine.html
liumify-2.0.0.dist-info/METADATA
liumify-2.0.0.dist-info/WHEEL
liumify-2.0.0.dist-info/top_level.txt
liumify-2.0.0.dist-info/RECORD
