Metadata-Version: 2.4
Name: liumify
Version: 2.0.0
Summary: The Gold Standard of Pythonic Visuals. Proprietary Internal Tool.
Author-email: Liumi Corporation Architecture Team <architect@liumi.cloud>
Project-URL: Homepage, https://liumi.cloud/liumify
Project-URL: Documentation, https://liumi.cloud/liumify/docs
Classifier: Development Status :: 5 - Production/Stable
Classifier: Intended Audience :: Developers
Classifier: Programming Language :: Python :: 3
Classifier: Operating System :: OS Independent
Requires-Python: >=3.9
Requires-Dist: fastapi>=0.100.0
Requires-Dist: uvicorn>=0.23.0
Requires-Dist: websockets>=11.0
Requires-Dist: jinja2>=3.1.0
Requires-Dist: pydantic>=2.0.0
